epitran/__init__.py
epitran/_epitran.py
epitran/backoff.py
epitran/cedict.py
epitran/dictfirst.py
epitran/download.py
epitran/epihan.py
epitran/exceptions.py
epitran/flite.py
epitran/ligaturize.py
epitran/meta.py
epitran/ppprocessor.py
epitran/puncnorm.py
epitran/reromanize.py
epitran/rules.py
epitran/simple.py
epitran/space.py
epitran/stripdiacritics.py
epitran/tir2pp.py
epitran/vector.py
epitran/xsampa.py
epitran/bin/connl2engipaspace.py
epitran/bin/connl2ipaspace.py
epitran/bin/decompose.py
epitran/bin/detectcaps.py
epitran/bin/epitranscribe.py
epitran/bin/extract_test_cases.py
epitran/bin/isbijective.py
epitran/bin/ltf2ipaspace.py
epitran/bin/migraterules.py
epitran/bin/reromanize.py
epitran/bin/space2punc.py
epitran/bin/testvectorgen.py
epitran/bin/uigtransliterate.py
epitran/bin/vie-tones.py
epitran/data/arpabet.csv
epitran/data/ipa-xsampa.csv
epitran/data/puncnorm.csv
epitran/data/sample.json
epitran/data/bib/deu-Latn.bib
epitran/data/map/aar-Latn.csv
epitran/data/map/afr-Latn.csv
epitran/data/map/aii-Syrc.csv
epitran/data/map/amh-Ethi-pp.csv
epitran/data/map/amh-Ethi-red.csv
epitran/data/map/amh-Ethi.csv
epitran/data/map/ara-Arab.csv
epitran/data/map/ava-Cyrl.csv
epitran/data/map/aze-Cyrl.csv
epitran/data/map/aze-Latn.csv
epitran/data/map/ben-Beng-east.csv
epitran/data/map/ben-Beng-red.csv
epitran/data/map/ben-Beng.csv
epitran/data/map/bho-Deva.csv
epitran/data/map/bxk-Latn.csv
epitran/data/map/cat-Latn.csv
epitran/data/map/ceb-Latn.csv
epitran/data/map/ces-Latn.csv
epitran/data/map/cjy-Latn.csv
epitran/data/map/ckb-Arab.csv
epitran/data/map/cmn-Latn.csv
epitran/data/map/count_phones.py
epitran/data/map/csb-Latn.csv
epitran/data/map/cym-Latn.csv
epitran/data/map/dan-Latn.csv
epitran/data/map/deu-Latn-nar.csv
epitran/data/map/deu-Latn-np.csv
epitran/data/map/deu-Latn.csv
epitran/data/map/epo-Latn.csv
epitran/data/map/est-Latn.csv
epitran/data/map/fas-Arab.csv
epitran/data/map/fin-Latn.csv
epitran/data/map/find_duplicates.py
epitran/data/map/fra-Latn-np.csv
epitran-1.34.0.dist-info/licenses/AUTHORS
epitran-1.34.0.dist-info/licenses/LICENSE.txt
epitran-1.34.0.dist-info/METADATA
epitran-1.34.0.dist-info/WHEEL
epitran-1.34.0.dist-info/top_level.txt
epitran-1.34.0.dist-info/zip-safe
epitran-1.34.0.dist-info/RECORD
