Metadata-Version: 2.4
Name: epitran
Version: 1.34.0
Summary: Tools for transcribing languages into IPA.
Author-email: "David R. Mortensen" <dmortens@cs.cmu.edu>
Maintainer-email: "David R. Mortensen" <dmortens@cs.cmu.edu>
License: MIT-Modern-Variant
Project-URL: Homepage, https://github.com/dmort27/epitran
Project-URL: Documentation, https://github.com/dmort27/epitran#readme
Project-URL: Repository, https://github.com/dmort27/epitran
Project-URL: Issues, https://github.com/dmort27/epitran/issues
Project-URL: Changelog, https://github.com/dmort27/epitran/releases
Keywords: linguistics,phonetics,IPA,transliteration,phonology
Classifier: Development Status :: 5 - Production/Stable
Classifier: Intended Audience :: Developers
Classifier: Intended Audience :: Science/Research
Classifier: Operating System :: OS Independent
Classifier: Programming Language :: Python :: 3
Classifier: Programming Language :: Python :: 3.10
Classifier: Programming Language :: Python :: 3.11
Classifier: Programming Language :: Python :: 3.12
Classifier: Programming Language :: Python :: 3.13
Classifier: Topic :: Software Development :: Libraries :: Python Modules
Classifier: Topic :: Text Processing :: Linguistic
Classifier: Topic :: Scientific/Engineering :: Artificial Intelligence
Requires-Python: >=3.10
License-File: LICENSE.txt
License-File: AUTHORS
Requires-Dist: regex
Requires-Dist: panphon>=0.20
Requires-Dist: marisa-trie
Requires-Dist: requests
Requires-Dist: jamo
Provides-Extra: dev
Requires-Dist: ruff; extra == "dev"
Dynamic: license-file
